pylighter/__init__.py
pylighter/annotation.py
pylighter/chunk_models.py
pylighter/config.py
pylighter/display.py
pylighter/loader.html
pylighter/merge.py
pylighter/utils.py
pylighter/css/color.css
pylighter/css/style.css
pylighter/js/key_shortcut.js
pylighter/js/key_shortcuts.js
pylighter/shortcut_helper/__init__.py
pylighter/shortcut_helper/shortcut_helper.js
pylighter/shortcut_helper/shortcut_helper.py
pylighter/toast/toast.css
pylighter/toast/toast.html
pylighter/toast/toast.js
pylighter-0.0.3.dist-info/LICENSE
pylighter-0.0.3.dist-info/METADATA
pylighter-0.0.3.dist-info/WHEEL
pylighter-0.0.3.dist-info/top_level.txt
pylighter-0.0.3.dist-info/RECORD
