Metadata-Version: 2.1
Name: pylighter
Version: 0.0.3
Summary: Annotation tool for NER tasks on Jupyter
Home-page: https://github.com/PayLead/PyLighter
Author: Etienne Turc
Author-email: etienne.turc@paylead.fr
License: MIT
Keywords: annotation,NER,Jupyter,labelize
Platform: UNKNOWN
Classifier: Development Status :: 5 - Production/Stable
Classifier: Intended Audience :: Developers
Classifier: Intended Audience :: Science/Research
Classifier: License :: OSI Approved :: MIT License
Classifier: Operating System :: OS Independent
Classifier: Programming Language :: Python
Classifier: Programming Language :: Python :: 3.7
Classifier: Programming Language :: Python :: 3.8
Classifier: Programming Language :: Python :: 3.9
Classifier: Topic :: Scientific/Engineering
Classifier: Topic :: Scientific/Engineering :: Artificial Intelligence
Requires-Python: >=3.7
Requires-Dist: ipython (>=7.18.1)
Requires-Dist: ipywidgets (>=7.5.1)
Requires-Dist: pandas (>=1.1.1)
Provides-Extra: dev
Requires-Dist: check-manifest ; extra == 'dev'
Requires-Dist: flake8 ; extra == 'dev'
Requires-Dist: isort (>=5.0.0) ; extra == 'dev'
Requires-Dist: tox ; extra == 'dev'
Requires-Dist: pytest (>=6.1.1) ; extra == 'dev'
Requires-Dist: wheel ; extra == 'dev'
Requires-Dist: zest.releaser[recommended] ; extra == 'dev'
